numfracpy/__init__.py
numfracpy-0.4.dist-info/METADATA
numfracpy-0.4.dist-info/WHEEL
numfracpy-0.4.dist-info/licenses/LICENSE
numfracpy-0.4.dist-info/RECORD
