Metadata-Version: 2.1
Name: numfracpy
Version: 0.4
Summary: This Library implements functions in the fractional calculus framework. 
Project-URL: Homepage, https://github.com/jhlopezm/NUMFRACPY
Project-URL: Bug Tracker, https://github.com/jhlopezm/NUMFRACPY/issues
Author-email: Jorge Hernan Lopez <jhlopezm2@gmail.com>, Alejandro Perez <aaappprrr@gmail.com>
License-File: LICENSE
Classifier: License :: OSI Approved :: MIT License
Classifier: Operating System :: OS Independent
Classifier: Programming Language :: Python :: 3
Requires-Python: >=3.7
